repo/__init__.py
repo/http_client.py
repo/manager.py
repo/repo.py
starbash/__init__.py
starbash/aliases.py
starbash/analytics.py
starbash/app.py
starbash/check_version.py
starbash/commands/__init__.py
starbash/commands/info.py
starbash/commands/process.py
starbash/commands/repo.py
starbash/commands/select.py
starbash/commands/user.py
starbash/database.py
starbash/defaults/__init__.py
starbash/defaults/starbash.toml
starbash/doit.py
starbash/doit_types.py
starbash/dwarf3.py
starbash/exception.py
starbash/filtering.py
starbash/icon.py
starbash/linux.py
starbash/main.py
starbash/os.py
starbash/parameters.py
starbash/paths.py
starbash/processed_target.py
starbash/processing.py
starbash/processing_like.py
starbash/recipes/README.md
starbash/recipes/__init__.py
starbash/recipes/osc.py
starbash/rich.py
starbash/safety.py
starbash/score.py
starbash/selection.py
starbash/sim_siril/__init__.py
starbash/sim_siril/connection.py
starbash/sim_siril/enums.py
starbash/sim_siril/utility.py
starbash/stage_utils.py
starbash/stages.py
starbash/templates/__init__.py
starbash/templates/repo/master.toml
starbash/templates/repo/processed.toml
starbash/templates/target/master.toml
starbash/templates/target/processed.toml
starbash/templates/userconfig.toml
starbash/toml.py
starbash/tool/__init__.py
starbash/tool/base.py
starbash/tool/context.py
starbash/tool/graxpert.py
starbash/tool/python.py
starbash/tool/siril.py
starbash/ui/main.py
starbash/url.py
starbash/windows.py
starbash-0.2.5.dist-info/METADATA
starbash-0.2.5.dist-info/WHEEL
starbash-0.2.5.dist-info/entry_points.txt
starbash-0.2.5.dist-info/licenses/LICENSE
starbash-0.2.5.dist-info/RECORD
