Metadata-Version: 2.4
Name: starbash
Version: 0.2.5
Summary: A tool for automating/standardizing/sharing astrophotography workflows.
License-File: LICENSE
Author: Kevin Hester
Author-email: kevinh@geeksville.com
Requires-Python: >=3.12,<3.15
Classifier: Programming Language :: Python :: 3
Classifier: Programming Language :: Python :: 3.12
Classifier: Programming Language :: Python :: 3.13
Classifier: Programming Language :: Python :: 3.14
Requires-Dist: astropy (>=7.1.1,<8.0.0)
Requires-Dist: doit (>=0.36.0,<0.37.0)
Requires-Dist: graxpert[cpuonly] (>=3.2.0a2,<4.0.0)
Requires-Dist: multidict (>=6.7.0,<7.0.0)
Requires-Dist: numpy (==2.2.6)
Requires-Dist: platformdirs (>=4.5.0,<5.0.0)
Requires-Dist: pyqt6 (>=6.10.1,<7.0.0)
Requires-Dist: requests-cache (>=1.2.1,<2.0.0)
Requires-Dist: restrictedpython (>=8.1,<9.0)
Requires-Dist: rich (>=14.2.0,<15.0.0)
Requires-Dist: sentry-sdk (>=2.42.1,<3.0.0)
Requires-Dist: textual (>=6.8.0,<7.0.0)
Requires-Dist: tomlkit (>=0.13.3,<0.14.0)
Requires-Dist: typer (>=0.20.0,<0.21.0)
Requires-Dist: update-checker (>=0.18.0,<0.19.0)
Project-URL: Documentation, https://github.com/geeksville/starbash/blob/main/README.md
Project-URL: Homepage, https://github.com/geeksville/starbash
Project-URL: Repository, https://github.com/geeksville/starbash
